shutterstock_analysis/__init__.py
shutterstock_analysis/shutterstock.py
shutterstock_analysis-0.0.2.dist-info/METADATA
shutterstock_analysis-0.0.2.dist-info/WHEEL
shutterstock_analysis-0.0.2.dist-info/top_level.txt
shutterstock_analysis-0.0.2.dist-info/RECORD
