Metadata-Version: 2.1
Name: shutterstock-analysis
Version: 0.0.2
Summary: The internet's very first python package supports analyzing the Shutterstock public data, which helps creators optimize their creative portfolio and earn more income with less effort.
Home-page: https://github.com/thinh-vu/vnnews
Author: Thinh Vu
Author-email: mrthinh@live.com
Classifier: Programming Language :: Python :: 3
Classifier: License :: OSI Approved :: MIT License
Classifier: Operating System :: OS Independent
Requires-Python: >=3.7
